atap_corpus_timeline/CorpusTimeline.py
atap_corpus_timeline/CorpusVisualiser.py
atap_corpus_timeline/__init__.py
atap_corpus_timeline-0.2.3.dist-info/LICENSE
atap_corpus_timeline-0.2.3.dist-info/METADATA
atap_corpus_timeline-0.2.3.dist-info/WHEEL
atap_corpus_timeline-0.2.3.dist-info/RECORD
